MANIFEST.in
README.rst
setup.cfg
setup.py
versioneer.py
rstoolbox/__init__.py
rstoolbox/_version.py
rstoolbox.egg-info/PKG-INFO
rstoolbox.egg-info/SOURCES.txt
rstoolbox.egg-info/dependency_links.txt
rstoolbox.egg-info/requires.txt
rstoolbox.egg-info/top_level.txt
rstoolbox/analysis/SimilarityMatrix.py
rstoolbox/analysis/__init__.py
rstoolbox/analysis/sequence.py
rstoolbox/analysis/stats.py
rstoolbox/analysis/structure.py
rstoolbox/analysis/matrices/BLOSUM100
rstoolbox/analysis/matrices/BLOSUM30
rstoolbox/analysis/matrices/BLOSUM35
rstoolbox/analysis/matrices/BLOSUM40
rstoolbox/analysis/matrices/BLOSUM45
rstoolbox/analysis/matrices/BLOSUM50
rstoolbox/analysis/matrices/BLOSUM55
rstoolbox/analysis/matrices/BLOSUM60
rstoolbox/analysis/matrices/BLOSUM62
rstoolbox/analysis/matrices/BLOSUM65
rstoolbox/analysis/matrices/BLOSUM70
rstoolbox/analysis/matrices/BLOSUM75
rstoolbox/analysis/matrices/BLOSUM80
rstoolbox/analysis/matrices/BLOSUM85
rstoolbox/analysis/matrices/BLOSUM90
rstoolbox/analysis/matrices/BLOSUMN
rstoolbox/analysis/matrices/DAYHOFF
rstoolbox/analysis/matrices/GONNET
rstoolbox/analysis/matrices/IDENTITY
rstoolbox/analysis/matrices/MATCH
rstoolbox/analysis/matrices/NUC.4.2
rstoolbox/analysis/matrices/NUC.4.4
rstoolbox/analysis/matrices/PAM10
rstoolbox/analysis/matrices/PAM100
rstoolbox/analysis/matrices/PAM110
rstoolbox/analysis/matrices/PAM120
rstoolbox/analysis/matrices/PAM130
rstoolbox/analysis/matrices/PAM140
rstoolbox/analysis/matrices/PAM150
rstoolbox/analysis/matrices/PAM160
rstoolbox/analysis/matrices/PAM170
rstoolbox/analysis/matrices/PAM180
rstoolbox/analysis/matrices/PAM190
rstoolbox/analysis/matrices/PAM20
rstoolbox/analysis/matrices/PAM200
rstoolbox/analysis/matrices/PAM210
rstoolbox/analysis/matrices/PAM220
rstoolbox/analysis/matrices/PAM230
rstoolbox/analysis/matrices/PAM240
rstoolbox/analysis/matrices/PAM250
rstoolbox/analysis/matrices/PAM260
rstoolbox/analysis/matrices/PAM270
rstoolbox/analysis/matrices/PAM280
rstoolbox/analysis/matrices/PAM290
rstoolbox/analysis/matrices/PAM30
rstoolbox/analysis/matrices/PAM300
rstoolbox/analysis/matrices/PAM310
rstoolbox/analysis/matrices/PAM320
