Metadata-Version: 1.1
Name: rstoolbox
Version: 1.0.0
Summary: management and analysis of design populations
Home-page: https://github.com/jaumebonet/RosettaSilentToolbox
Author: Jaume Bonet
Author-email: jaume.bonet@gmail.com
License: MIT
Project-URL: Documentation, http://jaumebonet.cat/RosettaSilentToolbox
Project-URL: Source, https://github.com/jaumebonet/RosettaSilentToolbox/
Project-URL: Tracker, https://github.com/jaumebonet/RosettaSilentToolbox/issues
Keywords: development
Platform: UNIX
Classifier: Development Status :: 5 - Production/Stable
Classifier: Intended Audience :: Developers
Classifier: Intended Audience :: Science/Research
Classifier: Environment :: Console
Classifier: License :: OSI Approved :: MIT License
Classifier: Programming Language :: Python :: 2
Classifier: Programming Language :: Python :: 2.7
Classifier: Programming Language :: Python :: 3
Classifier: Programming Language :: Python :: 3.4
Classifier: Programming Language :: Python :: 3.5
Classifier: Programming Language :: Python :: 3.6
Classifier: Programming Language :: Python :: 3.7
Classifier: Operating System :: MacOS
Classifier: Operating System :: Unix
Classifier: Topic :: Scientific/Engineering :: Bio-Informatics
Classifier: Topic :: Scientific/Engineering :: Visualization
